{
  "bioguide": "S001183",
  "name_en": "David Schweikert",
  "name_cn": "大卫·施韦克特",
  "party": "Republican",
  "state": "AZ",
  "district": 1,
  "chamber": "house",
  "type": "Representative",
  "tier": 2,
  "birthday": "1962-03-03",
  "gender": "M",
  "committees": {
    "all": [
      "House Committee on Ways and Means",
      "Joint Economic Committee"
    ],
    "china_related": [
      "House Committee on Ways and Means",
      "Joint Economic Committee"
    ],
    "leadership_role": ""
  },
  "social_media": {
    "twitter": "RepDavid",
    "wikipedia": "David Schweikert",
    "url": "https://schweikert.house.gov"
  },
  "source": "house/committee-ways-means/david-schweikert.md",
  "profile_md": "# David Schweikert（大卫·施韦克特）\n\n## 基本信息\n\n| 项目 | 内容 |\n|------|------|\n| **全名** | David Sheridan Schweikert |\n| **职务** | 美国众议员（亚利桑那州第1国会选区） |\n| **党派** | 共和党 |\n| **选区** | 亚利桑那州第1国会选区（2023年前为第6选区） |\n| **众议院任期** | 2011年1月3日至今（第8届） |\n| **出生** | 1962年3月3日（64岁），加利福尼亚州洛杉矶 |\n| **教育** | 亚利桑那州立大学（BA，1985；MBA，1988） |\n| **宗教信仰** | 天主教（Roman Catholic） |\n| **配偶** | 离婚 |\n| **子女** | 2人 |\n\n---\n\n## 政治履历\n\n### 早期职业生涯\n\n- 亚利桑那州立大学毕业后在房地产和金融行业工作\n- 曾任亚利桑那州众议院议员（1991–1994），年仅29岁当选\n- 1995–1999：亚利桑那州税务委员会委员（Maricopa County Treasurer's Office Deputy）\n- 曾创办房地产投资公司\n\n### 政治生涯 timeline\n\n| 时间 | 职位 | 备注 |\n|------|------|------|\n| 1991–1994 | 亚利桑那州众议院议员 | 代表Scottsdale地区 |\n| 2004、2006、2008 | 多次竞选联邦众议员 | 2004年参选AZ-01未果；2008年参选AZ-05未果 |\n| 2010 | 当选联邦众议员AZ-06 | 以52%–45%击败民主党现任Harry Mitchell |\n| 2011.1至今 | 美国众议员 | 2013年后选区重划为AZ-06，2023年后改为AZ-01 |\n| 2017–2019 | 众议院筹款委员会贸易小组委员会主席 | — |\n| 2023至今 | 联合经济委员会（JEC）主席 | 主管经济政策研究 |\n| 2026 | 竞选亚利桑那州州长 | 正在参与共和党初选 |\n\n### 关键事件\n\n- **2020年7月**：因竞选资金违规被众议院伦理委员会调查\n- **2022年**：FEC调查发现其竞选账户存在严重违规，个人被罚款$50,000；选举中以微弱优势连任\n- **2024年**：成功连任第7届，得票率约52%\n- **2026年**：宣布竞选亚利桑那州州长，不寻求连任众议员\n\n---\n\n## 对华立场分析\n\n### 总体定位：温和鹰派——支持对华贸易执法，倾向自由贸易原则\n\nSchweikert 在涉华议题上总体属于共和党主流立场，支持对华强硬贸易执法，但骨子里的自由贸易倾向使他不像部分极端鹰派那样主张全面脱钩。\n\n### 关键立场\n\n| 议题 | 立场 | 具体表现 |\n|------|------|---------|\n| **对华总体态度** | 温和鹰派 | 支持对华贸易施压，但主张通过谈判解决问题 |\n| **贸易** | 执法导向 | 支持反倾销措施和贸易救济，反对\"不公平贸易行为\" |\n| **技术竞争** | 支持管制 | 支持对华芯片出口限制和技术保护 |\n| **关税** | 谨慎支持 | 2020年欢迎第一阶段贸易协议；2025年对特朗普全面关税持保留态度 |\n\n### 涉华关键行动记录\n\n1. **2020年1月**：作为筹款委员会贸易小组委员会成员，发表声明支持美中第一阶段贸易协议\n2. **2023年**：联合经济委员会（JEC）发布多份关于中美经济竞争的报告\n3. **多次投票**：支持针对中国技术转让和知识产权保护的相关立法\n\n---\n\n## 核心政治主张\n\n| 议题 | 立场 |\n|------|------|\n| **经济** | 保守派。主张减税、放松监管、平衡预算。联合经济委员会主席，关注债务和赤字问题。曾称若不加控制将面临\"金融浩劫\"（financial armageddon） |\n| **医疗** | 支持替代奥巴马医保（ACA），主张市场导向改革 |\n| **移民** | 支持加强边境安全，但支持DACA受益者保护 |\n| **技术/加密货币** | 区块链和加密货币倡议者，共和党共同主席之一，主张\"科技不应该是党派问题\" |\n| **气候** | 不强调气候变化议题，倾向市场解决方案 |\n| **2020大选** | 2021年1月6日认证选举结果，但曾对选举程序表示质疑 |\n\n---\n\n## 利益关系与金主\n\n### 主要资金来源\n\n根据 OpenSecrets 数据：\n\n| 行业/来源 | 说明 |\n|-----------|------|\n| **房地产** | 行业背景深厚，为最大捐赠方之一 |\n| **金融/保险** | 银行、保险、投资行业大量捐赠 |\n| **科技/加密货币** | 区块链相关企业捐赠显著 |\n| **传统能源** | 石油天然气行业中等支持 |\n\n### 利益关联\n\n- **联合经济委员会（JEC）**：作为主席主导经济政策话语\n- **区块链核心小组**：共同主席，与加密货币行业关系密切\n- **保守派智库**：与Heritage Foundation等保守派智库保持联系\n\n---\n\n## 媒体报道摘要\n\n### 1. Arizona Republic（2025年2月）\n> 报道 Schweikert 在众议院发表演讲，警告共和党债务削减方案可能导致\"金融浩劫\"，显示其财政保守但务实的立场。\n\n### 2. Roll Call（2024年10月）\n> 分析 Schweikert 在亚利桑那州第1选区的激烈连任选战，突出其在边境和经济议题上的立场。\n\n### 3. YouTube / Fox Business（2025年2月）\n> \"GOP Rep. Schweikert urges Congress to avoid 'financial armageddon'\"——在众议院批评共和党债务削减和支出计划。\n\n### 4. AZ Central（2026年5月）\n> Schweikert 正式宣布竞选亚利桑那州州长，获多位共和党人士支持。\n\n---\n\n## 综合评价\n\nDavid Schweikert 从2011年起服务众议院，是筹款委员会贸易小组和联合经济委员会的资深成员。**他是财政保守派但有务实倾向**，在债务和预算议题上敢于挑战本党立场。\n\n**对华方面**：作为筹款委员会成员，他积极关注对华贸易问题，但总体立场以\"执法\"为基调，并非极端鹰派。他更倾向于通过世贸组织和双边机制解决贸易争端，而非全面对抗。\n\n**风险关注点**：竞选资金违规历史（FEC罚款$50,000）和伦理调查是其政治包袱；2026年州长竞选面临激烈初选竞争。\n\n---\n\n*数据来源：Wikipedia、OpenSecrets、Ballotpedia、AZ Central、Roll Call、The Hill*\n*更新时间：2026年6月*\n"
}