{
  "bioguide": "M000871",
  "name_en": "Tracey Mann",
  "name_cn": "特雷西·曼",
  "party": "Republican",
  "state": "KS",
  "district": 1,
  "chamber": "house",
  "type": "Representative",
  "tier": 3,
  "birthday": "1976-12-17",
  "gender": "M",
  "committees": {
    "all": [
      "House Committee on Agriculture",
      "House Committee on Transportation and Infrastructure"
    ],
    "china_related": [],
    "leadership_role": ""
  },
  "social_media": {
    "twitter": "RepMann",
    "wikipedia": "Tracey Mann",
    "url": "https://mann.house.gov"
  },
  "source": "house/no-committee/tracey-mann.md",
  "profile_md": "# 特雷西·曼（Tracey Mann）\n\n## 基本信息\n\n| 项目 | 内容 |\n|------|------|\n| **全名** | Tracey Robert Mann |\n| **职务** | 美国众议院堪萨斯州第1国会选区众议员 |\n| **党派** | 共和党 |\n| **选区** | 堪萨斯州第1国会选区（R+24，全美最共和党化农业选区之一） |\n| **众议院任期** | 2021年1月3日至今（第3届） |\n| **出生** | 1976年12月17日（49岁），堪萨斯州Gove County |\n| **教育** | 堪萨斯州立大学（BS农业经济学） |\n| **宗教信仰** | 基督教 |\n| **配偶** | Audrey Haynes（2002年结婚） |\n| **子女** | 4人 |\n\n---\n\n## 政治履历\n\n### 早期职业生涯\n\n- 在家族农场长大，第五代堪萨斯人\n- 大学期间在国会议员办公室实习\n- 从事房地产和农业生意\n- **2018-2019年**：担任堪萨斯州副州长（由州长Jeff Colyer任命）\n\n### 政治生涯时间线\n\n| 时间 | 职位 | 备注 |\n|------|------|------|\n| 2018.2-2019.1 | 堪萨斯州副州长 | 由州长Colyer任命 |\n| 2021.1至今 | 美国众议院堪萨斯第1选区议员 | 接替Roger Marshall |\n| 至今 | 众议院农业委员会成员 | — |\n| 至今 | 众议院交通和基础设施委员会成员 | — |\n\n### 关键事件\n\n- **2021年**：投票反对认证亚利桑那州和宾夕法尼亚州大选结果\n- **2022年**：投票反对《通胀削减法案》\n- **2023年**：在农业法案谈判中推动农民利益\n- **2024年**：投票反对乌克兰援助法案\n\n---\n\n## 对华立场分析\n\n### 总体定位：务实鹰派——农业利益使其对华贸易采取更务实态度\n\n曼所在的大第一区是全美最大单一国会选区之一，农业是经济支柱。作为农业委员会成员，他的立场受堪萨斯州农产品出口利益显著影响。\n\n### 关键立场\n\n| 议题 | 立场 | 具体表现 |\n|------|------|---------|\n| **对华总体态度** | 务实鹰派 | 政治上鹰派，但对华贸易战影响农业出口 |\n| **贸易** | 务实 | 农业利益使其关注中国市场准入 |\n| **技术竞争** | 支持限制 | 支持《芯片法案》 |\n\n### 涉华关键行动记录\n\n1. **投票支持《芯片与科学法案》（2022年）**\n2. 作为农业委员会成员，关注中美第一阶段贸易协议对大豆和谷物出口的执行情况\n3. 投票支持对华关税，但关注贸易战对农业的影响\n\n---\n\n## 核心政治主张\n\n| 议题 | 立场 |\n|------|------|\n| **社会议题** | 保守派。反对堕胎，支持传统价值观 |\n| **经济** | 财政保守。支持减税，反对增税 |\n| **环境** | 质疑气候变化科学。支持能源独立 |\n| **移民** | 强硬派。支持边境安全 |\n| **医疗** | 反对奥巴马医改 |\n| **国防** | 支持强势国防 |\n| **教育** | 支持学校选择 |\n| **其他** | 农业和农村发展是核心关注 |\n\n---\n\n## 利益关系与金主\n\n### 主要资金来源\n\n| 行业/来源 | 说明 |\n|-----------|------|\n| **农业行业** | 农业综合企业和农场组织 |\n| **保守派PAC** | 共和党保守派PAC |\n| **房地产** | 从业背景带来的相关捐赠 |\n| **能源行业** | 传统能源支持 |\n\n### 利益关联组织\n\n- **Republican Study Committee**：成员\n- **Agriculture Committee**：核心委员会职位\n- **Congressional Rural Caucus**：成员\n- **Republican Main Street Partnership**：成员\n\n---\n\n## 媒体报道摘要\n\n### 1. Kansas City Star（2021年）\n> 新科堪萨斯众议员Tracey Mann进入大第一区席位，誓言为农业和农村社区奋斗。\n\n### 2. WIBW（2022年）\n> Mann投票反对《通胀削减法案》，称其让堪萨斯农民失望。\n\n### 3. High Plains/Midwest Ag Journal（2023年）\n> Mann表示农业法案必须保护作物保险并为生产者提供强力安全网。\n\n---\n\n## 综合评价\n\n### 总体评价\n\nTracey Mann是代表堪萨斯州农业区的保守派共和党人。曾任堪萨斯州副州长，2021年进入国会。政治议程以农业和农村发展为核心。基本遵循共和党路线，但有时表现出务实倾向。\n\n### 对华评价\n\n在对华问题上面临两难：政治上支持对华强硬，但选区严重依赖农产品出口，包括对中国的大豆和谷物出口。支持技术竞争措施，但关注贸易战对农业影响。\n\n### 政治风险评估\n\n选区极其安全（R+24），基本无连任风险。可能考虑未来竞选堪萨斯州长或参议员。\n\n---\n\n*数据来源：Wikipedia、OpenSecrets、Congress.gov、Ballotpedia、媒体报道*\n*更新时间：2026年7月*\n"
}